newspresso/__init__.py
newspresso/main.py
newspresso/prompts.py
newspresso-2025.12.21175020.dist-info/METADATA
newspresso-2025.12.21175020.dist-info/WHEEL
newspresso-2025.12.21175020.dist-info/top_level.txt
newspresso-2025.12.21175020.dist-info/RECORD
