Metadata-Version: 2.4
Name: newspresso
Version: 2025.12.21175020
Summary: A new package that processes text-based news or announcement summaries, such as changes in chart inclusion rules for platforms like YouTube on the U.S. Billboard Charts. It uses structured LLM interac
Author-email: newspresso <hi@eugene.plus>
License: MIT
Project-URL: Homepage, https://github.com/chigwell/newspresso
Requires-Python: >=3.9
Requires-Dist: langchain-llm7>=0.0.0
Requires-Dist: llmatch-messages>=0.0.0
Requires-Dist: langchain-core>=0.3.0
